neffint/__init__.py
neffint/_version.py
neffint/adaptive_fourier_integral.py
neffint/fixed_grid_fourier_integral.py
neffint/utils.py
neffint-1.1.0.dist-info/LICENSE
neffint-1.1.0.dist-info/METADATA
neffint-1.1.0.dist-info/WHEEL
neffint-1.1.0.dist-info/top_level.txt
neffint-1.1.0.dist-info/RECORD
