Metadata-Version: 2.1
Name: neffint
Version: 1.1.0
Summary: Python package for computing Fourier integrals using a Filon type method with non-equidistant grid spacing.
Home-page: https://github.com/neffint/neffint/
Author: Eskil Vik, Nicolas Mounet
Requires-Python: >=3.7
License-File: LICENSE
Requires-Dist: numpy
Requires-Dist: scipy
Provides-Extra: core
Requires-Dist: numpy ; extra == 'core'
Requires-Dist: scipy ; extra == 'core'
Provides-Extra: docs
Requires-Dist: sphinx ; extra == 'docs'
Requires-Dist: sphinx-rtd-theme ; extra == 'docs'
Requires-Dist: nbsphinx ; extra == 'docs'
Requires-Dist: nbsphinx-link ; extra == 'docs'
Requires-Dist: ipykernel ; extra == 'docs'
Provides-Extra: test
Requires-Dist: pytest ; extra == 'test'
